{
  "personal": {
    "created_date": "2025-06-05",
    "form_of_address": "Sir",
    "last_login": "2025-06-15T16:27:45.264736",
    "name": "Sahi"
  },
  "preferences": {
    "brevity": "medium",
    "greetings": {
      "afternoon": "Good afternoon! What can I do for you?",
      "evening": "Good evening! What do you need?",
      "morning": "Good morning! How can I help you today?",
      "night": "Working late? How can I assist you?"
    },
    "voice": {
      "speed": 1,
      "tts_voice": "en-US-AriaNeural",
      "volume": 1
    }
  },
  "history": {
    "interactions": [
      {
        "parameters": {
          "query": "weather"
        },
        "text": "what is the weather",
        "timestamp": "2025-06-05T16:07:32.453418",
        "type": "provide_information"
      },
      {
        "parameters": {},
        "text": "open Chrome",
        "timestamp": "2025-06-05T16:09:08.750145",
        "type": "provide_information"
      },
      {
        "parameters": {},
        "text": "hello how are you",
        "timestamp": "2025-06-05T16:19:08.978552",
        "type": "provide_information"
      },
      {
        "parameters": {
          "query": "how r u"
        },
        "text": "how r u",
        "timestamp": "2025-06-05T16:23:15.625999",
        "type": "provide_information"
      },
      {
        "parameters": {
          "query": "weather"
        },
        "text": "what is the weather",
        "timestamp": "2025-06-05T16:24:01.762058",
        "type": "provide_information"
      },
      {
        "parameters": {
          "app_name": "chrome",
          "operation": "launch"
        },
        "text": "open Chrome",
        "timestamp": "2025-06-05T16:24:46.000688",
        "type": "app_control"
      },
      {
        "parameters": {},
        "text": "how r u",
        "timestamp": "2025-06-05T16:29:38.482396",
        "type": "provide_information"
      },
      {
        "parameters": {},
        "text": "how r u",
        "timestamp": "2025-06-05T16:30:13.994334",
        "type": "provide_information"
      },
      {
        "parameters": {
          "app_name": "Chrome",
          "operation": "launch"
        },
        "text": "open",
        "timestamp": "2025-06-05T16:30:47.488565",
        "type": "app_control"
      },
      {
        "parameters": {
          "query": "weather"
        },
        "text": "what is the weather",
        "timestamp": "2025-06-05T16:31:44.004394",
        "type": "provide_information"
      },
      {
        "parameters": {
          "query": "how are you today"
        },
        "text": "how are you today",
        "timestamp": "2025-06-05T16:33:56.393036",
        "type": "provide_information"
      },
      {
        "parameters": {
          "topic": "weather"
        },
        "text": "how are you",
        "timestamp": "2025-06-05T16:41:58.967244",
        "type": "provide_information"
      },
      {
        "parameters": {
          "app_name": "word",
          "operation": "launch"
        },
        "text": "open word",
        "timestamp": "2025-06-05T16:42:19.934356",
        "type": "app_control"
      },
      {
        "parameters": {
          "app_name": "chrome",
          "operation": "launch"
        },
        "text": "open chrome",
        "timestamp": "2025-06-05T16:42:40.373467",
        "type": "app_control"
      },
      {
        "parameters": {
          "query": "top 10 cars in world"
        },
        "text": "search for top 10 cars in world",
        "timestamp": "2025-06-05T16:43:02.452373",
        "type": "web_search"
      },
      {
        "parameters": {
          "app_name": "youtube",
          "operation": "launch"
        },
        "text": "open open youtube",
        "timestamp": "2025-06-05T16:43:20.947351",
        "type": "app_control"
      },
      {
        "parameters": {
          "content": "",
          "filename": "",
          "location": "desktop"
        },
        "text": "create a file in my desktop",
        "timestamp": "2025-06-05T16:43:42.868326",
        "type": "file_operation"
      },
      {
        "parameters": {
          "content": "High text content here...",
          "operation": "create_file"
        },
        "text": "create a high text on my desktop",
        "timestamp": "2025-06-05T16:44:22.091447",
        "type": "file_operation"
      },
      {
        "parameters": {
          "content": "",
          "filename": "hello.txt",
          "location": "desktop"
        },
        "text": "create a text file named hello and content is",
        "timestamp": "2025-06-05T16:44:50.103683",
        "type": "file_operation"
      },
      {
        "parameters": {},
        "text": "hi how are you",
        "timestamp": "2025-06-05T16:47:41.837153",
        "type": "provide_information"
      },
      {
        "parameters": {
          "app_name": "chrome",
          "operation": "launch"
        },
        "text": "can you open chrome",
        "timestamp": "2025-06-05T16:48:00.963366",
        "type": "app_control"
      },
      {
        "parameters": {
          "query": "top 10 cars in the world"
        },
        "text": "can you search top 10 cars in the world",
        "timestamp": "2025-06-05T16:48:23.083447",
        "type": "web_search"
      },
      {
        "parameters": {
          "content": "hi how are you",
          "filename": "hello.txt"
        },
        "text": "create a text file name hello txt and content is",
        "timestamp": "2025-06-05T16:48:43.521282",
        "type": "file_operation"
      },
      {
        "parameters": {},
        "text": "hi how are you",
        "timestamp": "2025-06-09T17:11:03.616495",
        "type": "provide_information"
      },
      {
        "parameters": {},
        "text": "what's on your mind",
        "timestamp": "2025-06-09T17:11:23.228198",
        "type": "provide_information"
      },
      {
        "parameters": {
          "query": "time"
        },
        "text": "what is the time now",
        "timestamp": "2025-06-09T17:13:04.097230",
        "type": "provide_information"
      },
      {
        "parameters": {
          "query": "weather"
        },
        "text": "what is the weather",
        "timestamp": "2025-06-09T17:13:27.809296",
        "type": "provide_information"
      },
      {
        "parameters": {},
        "text": "how are you",
        "timestamp": "2025-06-09T17:27:54.098562",
        "type": "provide_information"
      },
      {
        "parameters": {
          "operation": "off"
        },
        "text": "turn off the fan",
        "timestamp": "2025-06-09T17:28:38.557352",
        "type": "fan_control"
      },
      {
        "parameters": {
          "operation": "on"
        },
        "text": "turn on the fan",
        "timestamp": "2025-06-09T17:28:57.905441",
        "type": "fan_control"
      },
      {
        "parameters": {
          "operation": "off"
        },
        "text": "turn off the fan",
        "timestamp": "2025-06-09T17:30:15.261407",
        "type": "fan_control"
      },
      {
        "parameters": {},
        "text": "making",
        "timestamp": "2025-06-09T17:30:33.398914",
        "type": "provide_information"
      },
      {
        "parameters": {
          "operation": "on",
          "speed": "medium"
        },
        "text": "turn on the fan",
        "timestamp": "2025-06-09T17:31:21.688124",
        "type": "fan_control"
      },
      {
        "parameters": {
          "query": "time"
        },
        "text": "what's the time",
        "timestamp": "2025-06-09T17:31:42.868718",
        "type": "provide_information"
      },
      {
        "parameters": {
          "operation": "off"
        },
        "text": "turn off the fan",
        "timestamp": "2025-06-09T17:34:40.383931",
        "type": "fan_control"
      },
      {
        "parameters": {
          "operation": "on"
        },
        "text": "turn on the fan",
        "timestamp": "2025-06-09T17:34:59.867453",
        "type": "fan_control"
      },
      {
        "parameters": {
          "operation": "change_mode"
        },
        "text": "change the mood",
        "timestamp": "2025-06-09T17:35:17.861420",
        "type": "fan_control"
      },
      {
        "parameters": {
          "capabilities": [
            "Opening applications like VSCode, Chrome, Word, Excel, Notepad, etc.",
            "Searching the web for information",
            "Creating, reading, and modifying files",
            "Checking system information like time, date, and device status",
            "Controlling IoT devices, including a fan connected via ESP32",
            "Providing information on various topics",
            "Helping with calculations and conversions"
          ]
        },
        "text": "hi how are you",
        "timestamp": "2025-06-09T17:59:08.489733",
        "type": "provide_information"
      },
      {
        "parameters": {
          "operation": "on"
        },
        "text": "can you turn on",
        "timestamp": "2025-06-09T17:59:37.983120",
        "type": "fan_control"
      },
      {
        "parameters": {
          "operation": "off"
        },
        "text": "can you turn off the fan",
        "timestamp": "2025-06-09T17:59:57.485483",
        "type": "fan_control"
      },
      {
        "parameters": {
          "operation": "off"
        },
        "text": "can you turn off on the fan",
        "timestamp": "2025-06-09T18:01:00.855965",
        "type": "fan_control"
      },
      {
        "parameters": {
          "operation": "on"
        },
        "text": "turn on the fan",
        "timestamp": "2025-06-09T18:01:13.703903",
        "type": "fan_control"
      },
      {
        "parameters": {
          "operation": "on"
        },
        "text": "turn on the fan",
        "timestamp": "2025-06-09T18:02:04.045935",
        "type": "fan_control"
      },
      {
        "parameters": {},
        "text": "hi how are you",
        "timestamp": "2025-06-09T18:39:44.988220",
        "type": "provide_information"
      },
      {
        "parameters": {
          "operation": "off"
        },
        "text": "turn off the fan",
        "timestamp": "2025-06-09T18:40:03.498408",
        "type": "fan_control"
      },
      {
        "parameters": {
          "operation": "on"
        },
        "text": "turn on the fan",
        "timestamp": "2025-06-09T18:40:20.753807",
        "type": "fan_control"
      },
      {
        "parameters": {
          "operation": "off"
        },
        "text": "turn off the fan",
        "timestamp": "2025-06-09T19:54:03.162602",
        "type": "fan_control"
      },
      {
        "parameters": {
          "user_message": "how r u"
        },
        "text": "how r u",
        "timestamp": "2025-06-09T19:55:30.861116",
        "type": "provide_information"
      },
      {
        "parameters": {
          "app_name": "chrome",
          "operation": "launch"
        },
        "text": "open chrome",
        "timestamp": "2025-06-09T19:56:02.507395",
        "type": "app_control"
      },
      {
        "parameters": {
          "operation": "turn_off"
        },
        "text": "off the fan",
        "timestamp": "2025-06-09T19:58:48.527273",
        "type": "fan_control"
      },
      {
        "parameters": {
          "operation": "on"
        },
        "text": "turn on the fan",
        "timestamp": "2025-06-09T20:06:32.731927",
        "type": "fan_control"
      },
      {
        "parameters": {},
        "text": "hey",
        "timestamp": "2025-06-09T20:09:24.575961",
        "type": "provide_information"
      },
      {
        "parameters": {
          "operation": "on"
        },
        "text": "turn the fan on",
        "timestamp": "2025-06-09T20:12:36.787861",
        "type": "fan_control"
      },
      {
        "parameters": {
          "info_type": "time"
        },
        "text": "what is the time",
        "timestamp": "2025-06-09T20:13:15.700204",
        "type": "provide_information"
      },
      {
        "parameters": {},
        "text": "how are you",
        "timestamp": "2025-06-09T20:34:06.193791",
        "type": "provide_information"
      },
      {
        "parameters": {
          "operation": "on"
        },
        "text": "turn on the fan",
        "timestamp": "2025-06-09T20:34:34.047969",
        "type": "fan_control"
      },
      {
        "parameters": {},
        "text": "how r u",
        "timestamp": "2025-06-09T20:48:08.666691",
        "type": "provide_information"
      },
      {
        "parameters": {},
        "text": "hi how are you",
        "timestamp": "2025-06-09T20:50:22.474541",
        "type": "provide_information"
      },
      {
        "parameters": {
          "query": "time"
        },
        "text": "what is the time",
        "timestamp": "2025-06-09T20:51:24.515255",
        "type": "provide_information"
      },
      {
        "parameters": {
          "query": "weather"
        },
        "text": "what is the weather",
        "timestamp": "2025-06-09T20:51:47.017522",
        "type": "provide_information"
      },
      {
        "parameters": {},
        "text": "no thanks",
        "timestamp": "2025-06-09T20:52:16.585930",
        "type": "provide_information"
      },
      {
        "parameters": {},
        "text": "hi how are you",
        "timestamp": "2025-06-09T21:01:38.648620",
        "type": "provide_information"
      },
      {
        "parameters": {},
        "text": "what is the time",
        "timestamp": "2025-06-09T21:01:55.447750",
        "type": "provide_information"
      },
      {
        "parameters": {
          "query": "weather"
        },
        "text": "what is the weather",
        "timestamp": "2025-06-09T21:02:10.942802",
        "type": "provide_information"
      },
      {
        "parameters": {},
        "text": "hay how r u",
        "timestamp": "2025-06-09T21:19:29.964127",
        "type": "provide_information"
      },
      {
        "parameters": {},
        "text": "I am good",
        "timestamp": "2025-06-09T21:19:44.535098",
        "type": "provide_information"
      },
      {
        "parameters": {
          "query": "time"
        },
        "text": "what is the time",
        "timestamp": "2025-06-09T21:20:00.575953",
        "type": "provide_information"
      },
      {
        "parameters": {
          "original_query": "how r u"
        },
        "text": "how r u",
        "timestamp": "2025-06-09T22:13:27.353723",
        "type": "provide_information"
      },
      {
        "parameters": {
          "original_query": "open Chrome"
        },
        "text": "open Chrome",
        "timestamp": "2025-06-09T22:13:41.551114",
        "type": "provide_information"
      },
      {
        "parameters": {
          "original_query": "open application"
        },
        "text": "open application",
        "timestamp": "2025-06-09T22:13:59.939079",
        "type": "provide_information"
      },
      {
        "parameters": {
          "operation": "off",
          "original_query": "turn off the fan"
        },
        "text": "turn off the fan",
        "timestamp": "2025-06-09T22:14:15.758908",
        "type": "fan_control"
      },
      {
        "parameters": {
          "operation": "on",
          "original_query": "turn on the fan"
        },
        "text": "turn on the fan",
        "timestamp": "2025-06-09T22:14:32.498274",
        "type": "fan_control"
      },
      {
        "parameters": {
          "original_query": "start a project",
          "query": "start a project"
        },
        "text": "start a project",
        "timestamp": "2025-06-09T22:14:46.161546",
        "type": "provide_information"
      },
      {
        "parameters": {
          "original_query": "start a development",
          "query": "development"
        },
        "text": "start a development",
        "timestamp": "2025-06-09T22:15:18.763483",
        "type": "provide_information"
      },
      {
        "parameters": {
          "app_name": "VSCode",
          "operation": "open",
          "original_query": "open the website development project"
        },
        "text": "open the website development project",
        "timestamp": "2025-06-09T22:16:00.138607",
        "type": "app_control"
      },
      {
        "parameters": {
          "original_query": "list my projects"
        },
        "text": "list my projects",
        "timestamp": "2025-06-09T22:16:23.375942",
        "type": "provide_information"
      },
      {
        "parameters": {
          "original_query": "hi how are you"
        },
        "text": "hi how are you",
        "timestamp": "2025-06-09T22:18:55.920731",
        "type": "provide_information"
      },
      {
        "parameters": {
          "operation": "off",
          "original_query": "turn off the fan"
        },
        "text": "turn off the fan",
        "timestamp": "2025-06-09T22:19:09.519418",
        "type": "fan_control"
      },
      {
        "parameters": {
          "operation": "on",
          "original_query": "turn the fan back on"
        },
        "text": "turn the fan back on",
        "timestamp": "2025-06-09T22:19:48.363612",
        "type": "fan_control"
      },
      {
        "parameters": {
          "app_name": "youtube",
          "operation": "open",
          "original_query": "open youtube"
        },
        "text": "open youtube",
        "timestamp": "2025-06-09T22:20:08.237986",
        "type": "app_control"
      },
      {
        "parameters": {
          "original_query": "thank you"
        },
        "text": "thank you",
        "timestamp": "2025-06-09T22:20:36.572314",
        "type": "provide_information"
      },
      {
        "parameters": {
          "original_query": "no thanks bye"
        },
        "text": "no thanks bye",
        "timestamp": "2025-06-09T22:20:57.609536",
        "type": "provide_information"
      },
      {
        "parameters": {
          "original_query": "no thanks"
        },
        "text": "no thanks",
        "timestamp": "2025-06-09T22:21:11.666955",
        "type": "provide_information"
      },
      {
        "parameters": {
          "original_query": "weather report",
          "query": "weather report"
        },
        "text": "weather report",
        "timestamp": "2025-06-09T22:21:48.332525",
        "type": "provide_information"
      },
      {
        "parameters": {
          "app_name": "chrome",
          "operation": "launch",
          "original_query": "open Chrome"
        },
        "text": "open Chrome",
        "timestamp": "2025-06-09T22:23:00.642481",
        "type": "app_control"
      },
      {
        "parameters": {
          "original_query": "open application"
        },
        "text": "open application",
        "timestamp": "2025-06-09T22:23:36.917505",
        "type": "provide_information"
      },
      {
        "parameters": {
          "original_query": "open"
        },
        "text": "open",
        "timestamp": "2025-06-09T22:24:10.138560",
        "type": "provide_information"
      },
      {
        "parameters": {
          "app_name": "notepad",
          "operation": "open",
          "original_query": "open Notepad"
        },
        "text": "open Notepad",
        "timestamp": "2025-06-09T22:24:29.232926",
        "type": "app_control"
      },
      {
        "parameters": {
          "original_query": "who's your developer"
        },
        "text": "who's your developer",
        "timestamp": "2025-06-09T22:24:44.271691",
        "type": "provide_information"
      },
      {
        "parameters": {
          "original_query": "who's your owner"
        },
        "text": "who's your owner",
        "timestamp": "2025-06-09T22:25:09.282221",
        "type": "provide_information"
      },
      {
        "parameters": {
          "original_query": "who created you",
          "query": "owner"
        },
        "text": "who created you",
        "timestamp": "2025-06-09T22:25:51.576523",
        "type": "provide_information"
      },
      {
        "parameters": {
          "original_query": "who developed you",
          "query": "owner"
        },
        "text": "who developed you",
        "timestamp": "2025-06-09T22:26:20.531054",
        "type": "provide_information"
      },
      {
        "parameters": {
          "original_query": "my project list",
          "query": "my project list"
        },
        "text": "my project list",
        "timestamp": "2025-06-09T22:26:50.109902",
        "type": "provide_information"
      },
      {
        "parameters": {
          "original_query": "show my ongoing"
        },
        "text": "show my ongoing",
        "timestamp": "2025-06-09T22:27:21.772618",
        "type": "provide_information"
      },
      {
        "parameters": {
          "original_query": "Tell me a joke"
        },
        "text": "Tell me a joke",
        "timestamp": "2025-06-09T22:29:24.377708",
        "type": "provide_information"
      },
      {
        "parameters": {
          "operation": "change_mode",
          "original_query": "change the fan"
        },
        "text": "change the fan",
        "timestamp": "2025-06-09T22:33:03.591557",
        "type": "fan_control"
      },
      {
        "parameters": {
          "operation": "mode",
          "original_query": "change the fan mode"
        },
        "text": "change the fan mode",
        "timestamp": "2025-06-09T22:33:26.963556",
        "type": "fan_control"
      },
      {
        "parameters": {
          "operation": "speed_up",
          "original_query": "change the fan speed"
        },
        "text": "change the fan speed",
        "timestamp": "2025-06-09T22:33:39.401397",
        "type": "fan_control"
      },
      {
        "parameters": {
          "original_query": "Tell me a joke"
        },
        "text": "Tell me a joke",
        "timestamp": "2025-06-09T22:35:22.463143",
        "type": "provide_information"
      },
      {
        "parameters": {
          "original_query": "search 10",
          "query": "search 10"
        },
        "text": "search 10",
        "timestamp": "2025-06-09T22:35:49.313502",
        "type": "web_search"
      },
      {
        "parameters": {
          "original_query": "hi how are you"
        },
        "text": "hi how are you",
        "timestamp": "2025-06-10T00:28:35.624957",
        "type": "provide_information"
      },
      {
        "parameters": {
          "operation": "off",
          "original_query": "turn off the fan"
        },
        "text": "turn off the fan",
        "timestamp": "2025-06-10T00:28:48.355440",
        "type": "fan_control"
      },
      {
        "parameters": {
          "operation": "on",
          "original_query": "turn on the fan"
        },
        "text": "turn on the fan",
        "timestamp": "2025-06-10T00:29:03.013441",
        "type": "fan_control"
      },
      {
        "parameters": {
          "operation": "mode",
          "original_query": "turn the fan mode"
        },
        "text": "turn the fan mode",
        "timestamp": "2025-06-10T00:29:26.761903",
        "type": "fan_control"
      },
      {
        "parameters": {
          "operation": "speed_up",
          "original_query": "turn the fan speed up"
        },
        "text": "turn the fan speed up",
        "timestamp": "2025-06-10T00:29:46.140490",
        "type": "fan_control"
      },
      {
        "parameters": {
          "app_name": "chrome",
          "operation": "launch",
          "original_query": "open Chrome"
        },
        "text": "open Chrome",
        "timestamp": "2025-06-10T00:30:00.821847",
        "type": "app_control"
      },
      {
        "parameters": {
          "original_query": "I want to start a new project",
          "query": "I want to start a new project"
        },
        "text": "I want to start a new project",
        "timestamp": "2025-06-10T00:30:41.942983",
        "type": "provide_information"
      },
      {
        "parameters": {
          "command": "create",
          "file_type": "React project",
          "original_query": "start a react project"
        },
        "text": "start a react project",
        "timestamp": "2025-06-10T00:31:18.497683",
        "type": "file_operation"
      },
      {
        "parameters": {
          "original_query": "Mithun video Odia"
        },
        "text": "Mithun video Odia",
        "timestamp": "2025-06-10T00:31:41.647487",
        "type": "provide_information"
      },
      {
        "parameters": {
          "original_query": "list my projects",
          "query": "list my projects"
        },
        "text": "list my projects",
        "timestamp": "2025-06-10T00:32:06.494459",
        "type": "provide_information"
      },
      {
        "parameters": {
          "original_query": "list my projects",
          "query": "list my project"
        },
        "text": "list my project",
        "timestamp": "2025-06-10T00:39:54.570785",
        "type": "provide_information"
      },
      {
        "parameters": {
          "original_query": "list my projects",
          "query": "list my projects"
        },
        "text": "show my projects",
        "timestamp": "2025-06-10T00:40:19.500645",
        "type": "provide_information"
      },
      {
        "parameters": {
          "original_query": "end to the conver"
        },
        "text": "end to the conver",
        "timestamp": "2025-06-10T00:40:48.943755",
        "type": "provide_information"
      },
      {
        "parameters": {
          "original_query": "show my"
        },
        "text": "show my",
        "timestamp": "2025-06-10T00:41:06.892486",
        "type": "provide_information"
      },
      {
        "parameters": {
          "original_query": "show my existing projects",
          "query": "show my existing projects"
        },
        "text": "show my existing projects",
        "timestamp": "2025-06-10T00:41:24.223565",
        "type": "provide_information"
      },
      {
        "parameters": {
          "app_name": "VSCode",
          "operation": "open",
          "original_query": "open"
        },
        "text": "open",
        "timestamp": "2025-06-10T00:58:17.302050",
        "type": "app_control"
      },
      {
        "parameters": {
          "original_query": "no applist"
        },
        "text": "no applist",
        "timestamp": "2025-06-10T00:59:22.226595",
        "type": "provide_information"
      },
      {
        "parameters": {
          "original_query": "What time is it?",
          "query": "What time is it?"
        },
        "text": "What time is it?",
        "timestamp": "2025-06-10T00:59:51.450860",
        "type": "provide_information"
      },
      {
        "parameters": {
          "original_query": "Start voice recognition"
        },
        "text": "Start voice recognition",
        "timestamp": "2025-06-10T01:00:06.219552",
        "type": "provide_information"
      },
      {
        "parameters": {
          "original_query": "list my projects",
          "query": "list my projects"
        },
        "text": "listen list project",
        "timestamp": "2025-06-10T01:24:00.676199",
        "type": "provide_information"
      },
      {
        "parameters": {
          "original_query": "list project",
          "query": "list project"
        },
        "text": "list project",
        "timestamp": "2025-06-10T01:28:40.971990",
        "type": "provide_information"
      },
      {
        "parameters": {
          "original_query": "police projects",
          "query": "police projects"
        },
        "text": "police projects",
        "timestamp": "2025-06-10T01:29:29.974357",
        "type": "provide_information"
      },
      {
        "parameters": {
          "original_query": "list project",
          "query": "list my projects"
        },
        "text": "list project",
        "timestamp": "2025-06-10T01:30:51.343503",
        "type": "provide_information"
      },
      {
        "parameters": {
          "original_query": "please projects",
          "query": "projects"
        },
        "text": "please projects",
        "timestamp": "2025-06-10T01:32:05.104898",
        "type": "provide_information"
      },
      {
        "parameters": {
          "original_query": "list projects",
          "query": "list my projects"
        },
        "text": "list projects",
        "timestamp": "2025-06-10T01:32:33.721330",
        "type": "provide_information"
      },
      {
        "parameters": {
          "original_query": "list projects",
          "query": "list my projects"
        },
        "text": "list projects",
        "timestamp": "2025-06-10T01:33:23.352729",
        "type": "provide_information"
      },
      {
        "parameters": {
          "original_query": "hi how are you"
        },
        "text": "hi how are you",
        "timestamp": "2025-06-10T01:42:14.183195",
        "type": "provide_information"
      },
      {
        "parameters": {
          "original_query": "please command"
        },
        "text": "please command",
        "timestamp": "2025-06-10T01:42:47.663314",
        "type": "provide_information"
      },
      {
        "parameters": {
          "original_query": "list my projects",
          "query": "list my projects"
        },
        "text": "list projects",
        "timestamp": "2025-06-10T01:43:08.190877",
        "type": "provide_information"
      },
      {
        "parameters": {
          "original_query": "list my projects",
          "query": "list my projects"
        },
        "text": "list projects",
        "timestamp": "2025-06-10T01:46:12.909641",
        "type": "provide_information"
      },
      {
        "parameters": {
          "original_query": "hi how are you"
        },
        "text": "hi how are you",
        "timestamp": "2025-06-10T01:48:35.905070",
        "type": "provide_information"
      },
      {
        "parameters": {
          "original_query": "how r u"
        },
        "text": "how r u",
        "timestamp": "2025-06-10T01:51:25.710752",
        "type": "provide_information"
      },
      {
        "parameters": {
          "original_query": "list the projects",
          "query": "list the projects"
        },
        "text": "list the projects",
        "timestamp": "2025-06-10T01:51:40.856753",
        "type": "provide_information"
      },
      {
        "parameters": {
          "original_query": "please project"
        },
        "text": "please project",
        "timestamp": "2025-06-10T01:57:09.994919",
        "type": "provide_information"
      },
      {
        "parameters": {
          "original_query": "list project"
        },
        "text": "list project",
        "timestamp": "2025-06-10T01:57:40.350193",
        "type": "provide_information"
      },
      {
        "parameters": {
          "original_query": "list projects",
          "query": "list my projects"
        },
        "text": "list projects",
        "timestamp": "2025-06-10T01:57:53.872120",
        "type": "provide_information"
      },
      {
        "parameters": {
          "original_query": "agent"
        },
        "text": "agent",
        "timestamp": "2025-06-10T01:58:12.047730",
        "type": "provide_information"
      },
      {
        "parameters": {
          "app_name": "VSCode",
          "operation": "open",
          "original_query": "open agent project"
        },
        "text": "open agent project",
        "timestamp": "2025-06-10T01:58:33.745490",
        "type": "app_control"
      },
      {
        "parameters": {
          "original_query": "list my projects",
          "query": "list my projects"
        },
        "text": "list projects",
        "timestamp": "2025-06-10T01:59:26.680166",
        "type": "provide_information"
      },
      {
        "parameters": {
          "original_query": "portfolio",
          "query": "portfolio"
        },
        "text": "portfolio",
        "timestamp": "2025-06-10T01:59:47.733229",
        "type": "provide_information"
      },
      {
        "parameters": {
          "original_query": "I like to talk about cars"
        },
        "text": "I like to talk about cars",
        "timestamp": "2025-06-10T02:03:45.246670",
        "type": "provide_information"
      },
      {
        "parameters": {
          "original_query": "yeah I need to talk about cars"
        },
        "text": "yeah I need to talk about cars",
        "timestamp": "2025-06-10T02:04:03.580375",
        "type": "provide_information"
      },
      {
        "parameters": {
          "original_query": "I need to know what is the fastest car in the world"
        },
        "text": "I need to know what is the fastest car in the world",
        "timestamp": "2025-06-10T02:04:21.594365",
        "type": "provide_information"
      },
      {
        "parameters": {
          "original_query": "stop"
        },
        "text": "stop",
        "timestamp": "2025-06-10T02:05:41.591018",
        "type": "provide_information"
      },
      {
        "parameters": {
          "original_query": "what is the fastest car in the world",
          "query": "fastest car in the world"
        },
        "text": "what is the fastest car in the world",
        "timestamp": "2025-06-10T02:13:19.141403",
        "type": "provide_information"
      },
      {
        "parameters": {
          "original_query": "yeah go for it"
        },
        "text": "yeah go for it",
        "timestamp": "2025-06-10T02:13:58.299976",
        "type": "provide_information"
      },
      {
        "parameters": {
          "original_query": "yeah you should do is search about"
        },
        "text": "yeah you should do is search about",
        "timestamp": "2025-06-10T02:14:24.191272",
        "type": "provide_information"
      },
      {
        "parameters": {
          "original_query": "search for the cars"
        },
        "text": "search for the cars",
        "timestamp": "2025-06-10T02:14:48.163312",
        "type": "provide_information"
      },
      {
        "parameters": {
          "original_query": "this project"
        },
        "text": "this project",
        "timestamp": "2025-06-10T02:15:56.454037",
        "type": "provide_information"
      },
      {
        "parameters": {
          "original_query": "list my projects",
          "query": "list my projects"
        },
        "text": "list projects",
        "timestamp": "2025-06-10T02:16:18.895014",
        "type": "provide_information"
      },
      {
        "parameters": {
          "original_query": "list my projects",
          "query": "list my projects"
        },
        "text": "can you show the project again",
        "timestamp": "2025-06-10T02:18:54.025463",
        "type": "provide_information"
      },
      {
        "parameters": {
          "app_name": "vscode",
          "operation": "launch",
          "original_query": "create a project"
        },
        "text": "create a project",
        "timestamp": "2025-06-10T02:19:26.188234",
        "type": "app_control"
      },
      {
        "parameters": {
          "original_query": "python project"
        },
        "text": "python project",
        "timestamp": "2025-06-10T02:19:56.715501",
        "type": "provide_information"
      },
      {
        "parameters": {
          "app_name": "VSCode",
          "operation": "open",
          "original_query": "create that project"
        },
        "text": "create that project",
        "timestamp": "2025-06-10T02:20:19.388932",
        "type": "app_control"
      },
      {
        "parameters": {
          "original_query": "yes fuck yes"
        },
        "text": "yes fuck yes",
        "timestamp": "2025-06-10T02:21:00.523289",
        "type": "provide_information"
      },
      {
        "parameters": {
          "original_query": "stop persisting"
        },
        "text": "stop persisting",
        "timestamp": "2025-06-10T02:21:26.986709",
        "type": "provide_information"
      },
      {
        "parameters": {
          "original_query": "hi how are you"
        },
        "text": "hi how are you",
        "timestamp": "2025-06-10T12:33:43.609843",
        "type": "provide_information"
      },
      {
        "parameters": {
          "operation": "on",
          "original_query": "turn on my fan"
        },
        "text": "turn on my fan",
        "timestamp": "2025-06-10T12:34:04.194684",
        "type": "fan_control"
      },
      {
        "parameters": {
          "original_query": "is"
        },
        "text": "is",
        "timestamp": "2025-06-10T12:34:23.020222",
        "type": "provide_information"
      },
      {
        "parameters": {
          "operation": "on",
          "original_query": "turn on the fan"
        },
        "text": "turn on the fan",
        "timestamp": "2025-06-10T12:35:56.315700",
        "type": "fan_control"
      },
      {
        "parameters": {
          "operation": "change speed",
          "original_query": "change the speed for me"
        },
        "text": "change the speed for me",
        "timestamp": "2025-06-10T12:36:08.731860",
        "type": "fan_control"
      },
      {
        "parameters": {
          "operation": "speed",
          "original_query": "change the fan speed to medium",
          "speed": "medium"
        },
        "text": "change the fan speed to medium",
        "timestamp": "2025-06-10T12:36:26.846574",
        "type": "fan_control"
      },
      {
        "parameters": {
          "original_query": "open Chrome"
        },
        "text": "open Chrome",
        "timestamp": "2025-06-10T12:36:48.584037",
        "type": "provide_information"
      },
      {
        "parameters": {
          "original_query": "open Notepad"
        },
        "text": "open Notepad",
        "timestamp": "2025-06-10T12:37:11.856565",
        "type": "provide_information"
      },
      {
        "parameters": {
          "original_query": "open application"
        },
        "text": "open application",
        "timestamp": "2025-06-10T12:37:34.804108",
        "type": "provide_information"
      },
      {
        "parameters": {
          "app_name": "youtube",
          "operation": "launch",
          "original_query": "open YouTube"
        },
        "text": "open YouTube",
        "timestamp": "2025-06-10T12:37:58.912073",
        "type": "app_control"
      },
      {
        "parameters": {
          "original_query": "I want to start a"
        },
        "text": "I want to start a",
        "timestamp": "2025-06-10T12:38:15.863941",
        "type": "provide_information"
      },
      {
        "parameters": {
          "original_query": "I want to start a project list my project",
          "query": "list my projects"
        },
        "text": "I want to start a project list my project",
        "timestamp": "2025-06-10T12:38:41.739387",
        "type": "provide_information"
      },
      {
        "parameters": {
          "app_name": "VSCode",
          "operation": "launch",
          "original_query": "open project agent"
        },
        "text": "open project agent",
        "timestamp": "2025-06-10T12:39:14.355729",
        "type": "app_control"
      },
      {
        "parameters": {
          "app_name": "vscode",
          "operation": "launch",
          "original_query": "create new project"
        },
        "text": "new project",
        "timestamp": "2025-06-10T12:39:34.708104",
        "type": "app_control"
      },
      {
        "parameters": {
          "original_query": "what is the best car"
        },
        "text": "what is the best car",
        "timestamp": "2025-06-10T12:39:54.952578",
        "type": "provide_information"
      },
      {
        "parameters": {
          "original_query": "show me the fastest cars"
        },
        "text": "show me the fastest cars",
        "timestamp": "2025-06-10T12:40:39.510865",
        "type": "provide_information"
      },
      {
        "parameters": {
          "operation": "change mode",
          "original_query": "turn the speed of the fan",
          "speed": "medium"
        },
        "text": "turn the speed of the fan",
        "timestamp": "2025-06-10T18:01:23.138774",
        "type": "fan_control"
      },
      {
        "parameters": {
          "original_query": "open project"
        },
        "text": "open project",
        "timestamp": "2025-06-10T18:02:52.245581",
        "type": "provide_information"
      },
      {
        "parameters": {
          "original_query": "open the project"
        },
        "text": "open the project",
        "timestamp": "2025-06-10T18:03:19.951256",
        "type": "provide_information"
      },
      {
        "parameters": {
          "original_query": "open chrome"
        },
        "text": "open chrome",
        "timestamp": "2025-06-10T18:03:48.135747",
        "type": "provide_information"
      },
      {
        "parameters": {
          "original_query": "open Chrome"
        },
        "text": "open Chrome",
        "timestamp": "2025-06-10T18:15:24.412728",
        "type": "unknown"
      },
      {
        "parameters": {
          "original_query": "no thank you"
        },
        "text": "no thank you",
        "timestamp": "2025-06-10T18:15:45.465824",
        "type": "unknown"
      },
      {
        "parameters": {
          "original_query": "no thank you"
        },
        "text": "no thank you",
        "timestamp": "2025-06-10T18:16:04.071762",
        "type": "unknown"
      },
      {
        "parameters": {
          "original_query": "stop it"
        },
        "text": "stop it",
        "timestamp": "2025-06-10T18:16:26.812854",
        "type": "unknown"
      },
      {
        "parameters": {
          "operation": "change speed",
          "original_query": "change the fan speed"
        },
        "text": "change the fan speed",
        "timestamp": "2025-06-10T18:31:00.901115",
        "type": "fan_control"
      },
      {
        "parameters": {
          "operation": "change",
          "original_query": "change the fan"
        },
        "text": "change the fan",
        "timestamp": "2025-06-10T18:31:21.573099",
        "type": "fan_control"
      },
      {
        "parameters": {
          "operation": "off",
          "original_query": "turn off the fan"
        },
        "text": "turn off the fan",
        "timestamp": "2025-06-10T18:42:57.720338",
        "type": "fan_control"
      },
      {
        "parameters": {
          "operation": "on",
          "original_query": "turn on the fan"
        },
        "text": "turn on the fan",
        "timestamp": "2025-06-10T18:43:12.357432",
        "type": "fan_control"
      },
      {
        "parameters": {
          "original_query": "in conversation"
        },
        "text": "in conversation",
        "timestamp": "2025-06-10T18:43:26.790343",
        "type": "provide_information"
      },
      {
        "parameters": {
          "original_query": "turn off the fan for"
        },
        "text": "turn off the fan for",
        "timestamp": "2025-06-10T18:45:58.477013",
        "type": "provide_information"
      },
      {
        "parameters": {
          "original_query": "hello how are you"
        },
        "text": "hello how are you",
        "timestamp": "2025-06-10T18:46:50.311830",
        "type": "provide_information"
      },
      {
        "parameters": {
          "operation": "off",
          "original_query": "turn off the fan for"
        },
        "text": "turn off the fan for",
        "timestamp": "2025-06-10T18:47:12.267569",
        "type": "fan_control"
      },
      {
        "parameters": {
          "operation": "on",
          "original_query": "turn on the fan for"
        },
        "text": "turn on the fan for",
        "timestamp": "2025-06-10T18:47:24.190785",
        "type": "fan_control"
      },
      {
        "parameters": {
          "operation": "change speed",
          "original_query": "change the fan speed"
        },
        "text": "change the fan speed",
        "timestamp": "2025-06-10T18:47:35.801674",
        "type": "fan_control"
      },
      {
        "parameters": {
          "app_name": "chrome",
          "operation": "launch",
          "original_query": "open Chrome"
        },
        "text": "open Chrome",
        "timestamp": "2025-06-10T18:47:48.960160",
        "type": "app_control"
      },
      {
        "parameters": {
          "app_name": "YouTube",
          "operation": "launch",
          "original_query": "open YouTube"
        },
        "text": "open YouTube",
        "timestamp": "2025-06-10T18:47:57.646338",
        "type": "app_control"
      },
      {
        "parameters": {
          "app_name": "notepad",
          "operation": "open",
          "original_query": "open Notepad"
        },
        "text": "open Notepad",
        "timestamp": "2025-06-10T18:48:10.677998",
        "type": "app_control"
      },
      {
        "parameters": {
          "original_query": "project",
          "query": "list my projects"
        },
        "text": "project",
        "timestamp": "2025-06-10T18:48:24.166269",
        "type": "provide_information"
      },
      {
        "parameters": {
          "original_query": "hello kakas"
        },
        "text": "hello kakas",
        "timestamp": "2025-06-10T18:48:58.138960",
        "type": "provide_information"
      },
      {
        "parameters": {
          "original_query": "change the fan"
        },
        "text": "change the fan",
        "timestamp": "2025-06-10T21:44:02.719071",
        "type": "provide_information"
      },
      {
        "parameters": {
          "operation": "change mode",
          "original_query": "change the fan mode",
          "speed": "N"
        },
        "text": "change the fan mode",
        "timestamp": "2025-06-10T21:44:36.449112",
        "type": "fan_control"
      },
      {
        "parameters": {
          "operation": "change mode",
          "original_query": "change the fan mode"
        },
        "text": "change the fan mode",
        "timestamp": "2025-06-10T21:46:16.177532",
        "type": "fan_control"
      },
      {
        "parameters": {
          "original_query": "no thank you"
        },
        "text": "no thank you",
        "timestamp": "2025-06-10T21:47:09.832495",
        "type": "provide_information"
      },
      {
        "parameters": {
          "original_query": "stop"
        },
        "text": "stop",
        "timestamp": "2025-06-10T21:51:46.836064",
        "type": "end_conversation"
      },
      {
        "parameters": {
          "original_query": "how r u"
        },
        "text": "how r u",
        "timestamp": "2025-06-10T22:15:48.764585",
        "type": "provide_information"
      },
      {
        "parameters": {
          "original_query": "hi how are you"
        },
        "text": "hi how are you",
        "timestamp": "2025-06-10T22:20:55.862816",
        "type": "provide_information"
      },
      {
        "parameters": {
          "original_query": "stop the conversation"
        },
        "text": "stop the conversation",
        "timestamp": "2025-06-10T22:21:27.323266",
        "type": "provide_information"
      },
      {
        "parameters": {
          "original_query": "hi how are you"
        },
        "text": "hi how are you",
        "timestamp": "2025-06-10T22:35:13.236494",
        "type": "provide_information"
      },
      {
        "parameters": {
          "original_query": "hi how are you"
        },
        "text": "hi how are you",
        "timestamp": "2025-06-10T22:39:51.845783",
        "type": "provide_information"
      },
      {
        "parameters": {
          "original_query": "end the conver"
        },
        "text": "end the conver",
        "timestamp": "2025-06-10T22:40:10.554717",
        "type": "provide_information"
      },
      {
        "parameters": {
          "original_query": "hi how are you"
        },
        "text": "hi how are you",
        "timestamp": "2025-06-10T22:41:56.538230",
        "type": "provide_information"
      },
      {
        "parameters": {
          "original_query": "hello"
        },
        "text": "hello",
        "timestamp": "2025-06-10T22:42:22.026415",
        "type": "provide_information"
      },
      {
        "parameters": {
          "_prevent_speech": true,
          "original_query": "hi how are you"
        },
        "text": "hi how are you",
        "timestamp": "2025-06-10T22:48:00.305698",
        "type": "provide_information"
      },
      {
        "parameters": {
          "_prevent_speech": true,
          "original_query": "I am good"
        },
        "text": "I am good",
        "timestamp": "2025-06-10T22:48:15.025808",
        "type": "provide_information"
      },
      {
        "parameters": {
          "_prevent_speech": true,
          "original_query": "can you"
        },
        "text": "can you",
        "timestamp": "2025-06-10T22:48:30.083644",
        "type": "provide_information"
      },
      {
        "parameters": {
          "operation": "off",
          "original_query": "can you turn off the fan"
        },
        "text": "can you turn off the fan",
        "timestamp": "2025-06-10T22:48:45.732689",
        "type": "fan_control"
      },
      {
        "parameters": {
          "original_query": "thank you stop now"
        },
        "text": "thank you stop now",
        "timestamp": "2025-06-10T22:48:58.532783",
        "type": "provide_information"
      },
      {
        "parameters": {
          "_prevent_speech": true,
          "original_query": "hay how r u"
        },
        "text": "hay how r u",
        "timestamp": "2025-06-10T23:18:04.241556",
        "type": "provide_information"
      },
      {
        "parameters": {
          "operation": "on",
          "original_query": "turn on the fan"
        },
        "text": "turn on the fan",
        "timestamp": "2025-06-10T23:18:16.737780",
        "type": "fan_control"
      },
      {
        "parameters": {
          "original_query": "stop the conden"
        },
        "text": "stop the conden",
        "timestamp": "2025-06-10T23:18:27.211135",
        "type": "provide_information"
      },
      {
        "parameters": {
          "_prevent_speech": true,
          "original_query": "turn off the fan"
        },
        "text": "turn off the fan",
        "timestamp": "2025-06-10T23:35:34.575796",
        "type": "provide_information"
      },
      {
        "parameters": {
          "_prevent_speech": true,
          "original_query": "turn off the phone"
        },
        "text": "turn off the phone",
        "timestamp": "2025-06-10T23:35:47.588463",
        "type": "provide_information"
      },
      {
        "parameters": {
          "operation": "off",
          "original_query": "turn off the fan"
        },
        "text": "turn off the fan",
        "timestamp": "2025-06-10T23:35:59.111382",
        "type": "fan_control"
      },
      {
        "parameters": {
          "operation": "on",
          "original_query": "turn on the fan"
        },
        "text": "turn on the fan",
        "timestamp": "2025-06-10T23:36:06.796251",
        "type": "fan_control"
      },
      {
        "parameters": {
          "_prevent_speech": true,
          "original_query": "in the conversation"
        },
        "text": "in the conversation",
        "timestamp": "2025-06-10T23:36:17.652793",
        "type": "provide_information"
      },
      {
        "parameters": {
          "operation": "off",
          "original_query": "turn off the fan"
        },
        "text": "turn off the fan",
        "timestamp": "2025-06-11T00:55:05.487855",
        "type": "fan_control"
      },
      {
        "parameters": {
          "operation": "on",
          "original_query": "turn on the fan"
        },
        "text": "turn on the fan",
        "timestamp": "2025-06-11T00:57:16.327300",
        "type": "fan_control"
      },
      {
        "parameters": {
          "original_query": "top conversation"
        },
        "text": "top conversation",
        "timestamp": "2025-06-11T00:57:30.813842",
        "type": "provide_information"
      },
      {
        "parameters": {
          "operation": "off",
          "original_query": "turn the fan off"
        },
        "text": "turn the fan off",
        "timestamp": "2025-06-11T03:17:18.567894",
        "type": "fan_control"
      },
      {
        "parameters": {
          "_prevent_speech": true,
          "original_query": "hey how are you"
        },
        "text": "hey how are you",
        "timestamp": "2025-06-14T15:59:19.392631",
        "type": "provide_information"
      },
      {
        "parameters": {
          "_prevent_speech": true,
          "original_query": "Khushi hona",
          "query": "Khushi hona"
        },
        "text": "Khushi hona",
        "timestamp": "2025-06-14T16:00:20.027972",
        "type": "provide_information"
      },
      {
        "parameters": {
          "_prevent_speech": true,
          "original_query": "I need to know who is your"
        },
        "text": "I need to know who is your",
        "timestamp": "2025-06-14T16:00:38.753843",
        "type": "provide_information"
      },
      {
        "parameters": {
          "original_query": "who is your owner",
          "query": "owner"
        },
        "text": "who is your owner",
        "timestamp": "2025-06-14T16:00:52.483882",
        "type": "provide_information"
      },
      {
        "parameters": {
          "_prevent_speech": true,
          "original_query": "how are you"
        },
        "text": "how are you",
        "timestamp": "2025-06-14T16:13:38.675558",
        "type": "provide_information"
      },
      {
        "parameters": {
          "_prevent_speech": true,
          "original_query": "in conversation"
        },
        "text": "in conversation",
        "timestamp": "2025-06-14T16:13:51.190673",
        "type": "provide_information"
      },
      {
        "parameters": {
          "original_query": "conversation"
        },
        "text": "conversation",
        "timestamp": "2025-06-14T16:14:04.048651",
        "type": "provide_information"
      },
      {
        "parameters": {
          "_prevent_speech": true,
          "original_query": "hi how are you"
        },
        "text": "hi how are you",
        "timestamp": "2025-06-14T16:18:17.665238",
        "type": "provide_information"
      },
      {
        "parameters": {
          "original_query": "how r u"
        },
        "text": "how r u",
        "timestamp": "2025-06-14T16:23:43.543581",
        "type": "provide_information"
      },
      {
        "parameters": {
          "_prevent_speech": true,
          "original_query": "how are you"
        },
        "text": "how are you",
        "timestamp": "2025-06-14T16:24:16.942628",
        "type": "provide_information"
      },
      {
        "parameters": {
          "app_name": "chrome",
          "operation": "launch",
          "original_query": "open Chrome"
        },
        "text": "open Chrome",
        "timestamp": "2025-06-14T16:24:31.812343",
        "type": "app_control"
      },
      {
        "parameters": {
          "operation": "on",
          "original_query": "turn on the fan"
        },
        "text": "turn on the fan",
        "timestamp": "2025-06-14T16:54:43.620476",
        "type": "fan_control"
      },
      {
        "parameters": {
          "operation": "speed_up",
          "original_query": "increase the speed"
        },
        "text": "increase the speed",
        "timestamp": "2025-06-14T16:54:58.037030",
        "type": "fan_control"
      },
      {
        "parameters": {
          "operation": "increase_speed",
          "original_query": "increase the fan"
        },
        "text": "increase the fan",
        "timestamp": "2025-06-14T16:55:10.279175",
        "type": "fan_control"
      },
      {
        "parameters": {
          "operation": "status",
          "original_query": "what is the fan status"
        },
        "text": "what is the what is the fan status",
        "timestamp": "2025-06-14T16:55:26.312362",
        "type": "fan_control"
      },
      {
        "parameters": {
          "operation": "status",
          "original_query": "what is the fan status"
        },
        "text": "what is the fan status",
        "timestamp": "2025-06-14T16:56:23.068591",
        "type": "fan_control"
      },
      {
        "parameters": {
          "operation": "off",
          "original_query": "turn off the fan"
        },
        "text": "turn off the fan",
        "timestamp": "2025-06-14T17:00:56.871086",
        "type": "fan_control"
      },
      {
        "parameters": {
          "operation": "on",
          "original_query": "turn on the fan"
        },
        "text": "turn on the fan",
        "timestamp": "2025-06-14T17:03:01.656501",
        "type": "fan_control"
      },
      {
        "parameters": {
          "app_name": "steam",
          "operation": "launch",
          "original_query": "Open Steam"
        },
        "text": "Open Steam",
        "timestamp": "2025-06-14T17:06:49.580414",
        "type": "app_control"
      },
      {
        "parameters": {
          "app_name": "steam",
          "operation": "launch",
          "original_query": "Open Steam"
        },
        "text": "Open Steam",
        "timestamp": "2025-06-14T17:08:15.368589",
        "type": "app_control"
      },
      {
        "parameters": {
          "_prevent_speech": true,
          "original_query": "show available apps",
          "query": "list installed applications"
        },
        "text": "show available apps",
        "timestamp": "2025-06-14T17:30:34.171146",
        "type": "provide_information"
      },
      {
        "parameters": {
          "app_name": "discord",
          "operation": "launch",
          "original_query": "open discord"
        },
        "text": "open discord",
        "timestamp": "2025-06-14T17:31:27.959409",
        "type": "app_control"
      },
      {
        "parameters": {
          "app_name": "steam",
          "operation": "launch",
          "original_query": "Open Steam"
        },
        "text": "Open Steam",
        "timestamp": "2025-06-14T17:32:01.506092",
        "type": "app_control"
      },
      {
        "parameters": {
          "app_name": "chrome",
          "operation": "launch",
          "original_query": "open Chrome"
        },
        "text": "open Chrome",
        "timestamp": "2025-06-14T17:32:51.984722",
        "type": "app_control"
      },
      {
        "parameters": {
          "_prevent_speech": true,
          "original_query": "open post"
        },
        "text": "open post",
        "timestamp": "2025-06-14T17:33:20.696213",
        "type": "provide_information"
      },
      {
        "parameters": {
          "app_name": "postman",
          "operation": "launch",
          "original_query": "postman"
        },
        "text": "postman",
        "timestamp": "2025-06-14T17:33:36.414425",
        "type": "app_control"
      },
      {
        "parameters": {
          "app_name": "calculator",
          "operation": "launch",
          "original_query": "launch calculator"
        },
        "text": "launch calculator",
        "timestamp": "2025-06-14T17:34:20.968320",
        "type": "app_control"
      },
      {
        "parameters": {
          "app_name": "chrome",
          "operation": "launch",
          "original_query": "open chrome"
        },
        "text": "open chrome",
        "timestamp": "2025-06-14T17:34:42.203017",
        "type": "app_control"
      },
      {
        "parameters": {
          "original_query": "steam"
        },
        "text": "steam",
        "timestamp": "2025-06-14T17:34:55.199849",
        "type": "provide_information"
      },
      {
        "parameters": {
          "app_name": "spotify",
          "operation": "launch",
          "original_query": "open spotify"
        },
        "text": "open spotify",
        "timestamp": "2025-06-14T17:36:36.824926",
        "type": "app_control"
      },
      {
        "parameters": {
          "app_name": "steam",
          "operation": "launch",
          "original_query": "Open Steam"
        },
        "text": "Open Steam",
        "timestamp": "2025-06-14T17:37:24.814089",
        "type": "app_control"
      },
      {
        "parameters": {
          "_prevent_speech": true,
          "original_query": "show installed apps",
          "query": "show installed apps"
        },
        "text": "show installed apps",
        "timestamp": "2025-06-14T17:54:45.243986",
        "type": "provide_information"
      },
      {
        "parameters": {
          "app_name": "spotify",
          "operation": "launch",
          "original_query": "Open Spotify"
        },
        "text": "show installed apps",
        "timestamp": "2025-06-14T17:55:16.207424",
        "type": "app_control"
      },
      {
        "parameters": {
          "_prevent_speech": true,
          "original_query": "show available apps",
          "query": "show available apps"
        },
        "text": "show available apps",
        "timestamp": "2025-06-14T17:55:51.865611",
        "type": "provide_information"
      },
      {
        "parameters": {
          "app_name": "vscode",
          "operation": "launch",
          "original_query": "open vs"
        },
        "text": "open vs",
        "timestamp": "2025-06-14T17:56:35.651235",
        "type": "app_control"
      },
      {
        "parameters": {
          "app_name": "steam",
          "operation": "launch",
          "original_query": "open steam"
        },
        "text": "open steam",
        "timestamp": "2025-06-14T17:57:03.211437",
        "type": "app_control"
      },
      {
        "parameters": {
          "original_query": "establishing"
        },
        "text": "establishing",
        "timestamp": "2025-06-14T17:57:14.164999",
        "type": "provide_information"
      },
      {
        "parameters": {
          "_prevent_speech": true,
          "original_query": "hi how are you"
        },
        "text": "hi how are you",
        "timestamp": "2025-06-14T20:02:31.168537",
        "type": "provide_information"
      },
      {
        "parameters": {
          "app_name": "chrome",
          "operation": "launch",
          "original_query": "open Chrome"
        },
        "text": "open Chrome",
        "timestamp": "2025-06-14T20:02:43.681933",
        "type": "app_control"
      },
      {
        "parameters": {
          "app_name": "steam",
          "operation": "launch",
          "original_query": "Open Steam"
        },
        "text": "Open Steam",
        "timestamp": "2025-06-14T20:03:13.463124",
        "type": "app_control"
      },
      {
        "parameters": {
          "app_name": "SpeedGate",
          "operation": "launch",
          "original_query": "open speed Gate"
        },
        "text": "open speed Gate",
        "timestamp": "2025-06-14T20:04:30.289478",
        "type": "app_control"
      },
      {
        "parameters": {
          "_prevent_speech": true,
          "original_query": "split Gate to"
        },
        "text": "split Gate to",
        "timestamp": "2025-06-14T20:05:33.958411",
        "type": "provide_information"
      },
      {
        "parameters": {
          "app_name": "split gate",
          "operation": "launch",
          "original_query": "open split gate"
        },
        "text": "open split gate",
        "timestamp": "2025-06-14T20:05:53.552792",
        "type": "app_control"
      },
      {
        "parameters": {
          "_prevent_speech": true,
          "original_query": "thank"
        },
        "text": "thank",
        "timestamp": "2025-06-14T20:06:16.742992",
        "type": "provide_information"
      },
      {
        "parameters": {
          "original_query": "list apps",
          "query": "list installed applications"
        },
        "text": "list apps",
        "timestamp": "2025-06-14T20:08:52.960776",
        "type": "provide_information"
      },
      {
        "parameters": {
          "_prevent_speech": true,
          "original_query": "how are you hi"
        },
        "text": "how are you hi",
        "timestamp": "2025-06-14T20:14:44.779002",
        "type": "provide_information"
      },
      {
        "parameters": {
          "_prevent_speech": true,
          "original_query": "please my installed apps",
          "query": "list my installed apps"
        },
        "text": "please my installed apps",
        "timestamp": "2025-06-14T20:15:03.848419",
        "type": "provide_information"
      },
      {
        "parameters": {
          "_prevent_speech": true,
          "original_query": "list apps",
          "query": "list apps"
        },
        "text": "list apps",
        "timestamp": "2025-06-14T20:15:33.556994",
        "type": "provide_information"
      },
      {
        "parameters": {
          "app_name": "chrome",
          "operation": "launch",
          "original_query": "open Chrome"
        },
        "text": "open Chrome",
        "timestamp": "2025-06-14T20:17:02.918391",
        "type": "app_control"
      },
      {
        "parameters": {
          "_prevent_speech": true,
          "original_query": "allopathy"
        },
        "text": "allopathy",
        "timestamp": "2025-06-14T20:17:26.680097",
        "type": "provide_information"
      },
      {
        "parameters": {
          "app_name": "notepad",
          "operation": "open",
          "original_query": "open Notepad"
        },
        "text": "open Notepad",
        "timestamp": "2025-06-14T20:17:53.965841",
        "type": "app_control"
      },
      {
        "parameters": {
          "app_name": "split gate",
          "operation": "launch",
          "original_query": "open split gate"
        },
        "text": "open split gate",
        "timestamp": "2025-06-14T20:18:11.864429",
        "type": "app_control"
      },
      {
        "parameters": {
          "app_name": "vah frame",
          "operation": "open",
          "original_query": "open vah frame"
        },
        "text": "open vah frame",
        "timestamp": "2025-06-14T20:18:31.641416",
        "type": "app_control"
      },
      {
        "parameters": {
          "_prevent_speech": true,
          "original_query": "open vah frame"
        },
        "text": "open vah frame",
        "timestamp": "2025-06-14T20:19:02.681093",
        "type": "provide_information"
      },
      {
        "parameters": {
          "app_name": "vah frame",
          "operation": "open",
          "original_query": "open vah frame"
        },
        "text": "open vah frame",
        "timestamp": "2025-06-14T20:19:17.804058",
        "type": "app_control"
      },
      {
        "parameters": {
          "app_name": "speed Gate",
          "operation": "open",
          "original_query": "open speed Gate"
        },
        "text": "open speed Gate",
        "timestamp": "2025-06-14T20:20:13.470807",
        "type": "app_control"
      },
      {
        "parameters": {
          "_prevent_speech": true,
          "original_query": "open"
        },
        "text": "open",
        "timestamp": "2025-06-14T20:20:48.376775",
        "type": "provide_information"
      },
      {
        "parameters": {
          "app_name": "chrome",
          "operation": "launch",
          "original_query": "open Chrome"
        },
        "text": "open Chrome",
        "timestamp": "2025-06-14T20:21:01.656339",
        "type": "app_control"
      },
      {
        "parameters": {
          "app_name": "chrome",
          "operation": "launch",
          "original_query": "open everything"
        },
        "text": "open everything",
        "timestamp": "2025-06-14T20:21:15.628476",
        "type": "app_control"
      },
      {
        "parameters": {
          "_prevent_speech": true,
          "original_query": "open"
        },
        "text": "open",
        "timestamp": "2025-06-14T20:21:29.886992",
        "type": "provide_information"
      },
      {
        "parameters": {
          "app_name": "brave",
          "operation": "launch",
          "original_query": "open Brave"
        },
        "text": "open Brave",
        "timestamp": "2025-06-14T20:21:44.234387",
        "type": "app_control"
      },
      {
        "parameters": {
          "app_name": "everything",
          "operation": "launch",
          "original_query": "open everything app"
        },
        "text": "open everything app",
        "timestamp": "2025-06-14T20:22:03.893176",
        "type": "app_control"
      },
      {
        "parameters": {
          "app_name": "spotify",
          "operation": "launch",
          "original_query": "open Spotify"
        },
        "text": "open spotify",
        "timestamp": "2025-06-14T20:22:26.005219",
        "type": "app_control"
      },
      {
        "parameters": {
          "app_name": "steam",
          "operation": "launch",
          "original_query": "Open Steam"
        },
        "text": "Open Steam",
        "timestamp": "2025-06-14T20:22:46.158113",
        "type": "app_control"
      },
      {
        "parameters": {
          "_prevent_speech": true,
          "original_query": "shortlist"
        },
        "text": "shortlist",
        "timestamp": "2025-06-14T20:24:39.693006",
        "type": "provide_information"
      },
      {
        "parameters": {
          "_prevent_speech": true,
          "original_query": "show app list",
          "query": "show app list"
        },
        "text": "show app list",
        "timestamp": "2025-06-14T20:24:56.546486",
        "type": "provide_information"
      },
      {
        "parameters": {
          "_prevent_speech": true,
          "original_query": "show installed application"
        },
        "text": "show installed application",
        "timestamp": "2025-06-14T20:25:38.799401",
        "type": "provide_information"
      },
      {
        "parameters": {
          "original_query": "show instead application"
        },
        "text": "show instead application",
        "timestamp": "2025-06-14T20:26:08.325814",
        "type": "provide_information"
      },
      {
        "parameters": {
          "app_name": "steam",
          "operation": "launch",
          "original_query": "Open Steam"
        },
        "text": "Open Steam",
        "timestamp": "2025-06-14T20:27:39.142797",
        "type": "app_control"
      },
      {
        "parameters": {
          "app_name": "VSCode",
          "operation": "launch",
          "original_query": "open cursor"
        },
        "text": "open cursor",
        "timestamp": "2025-06-14T20:27:54.900589",
        "type": "app_control"
      },
      {
        "parameters": {
          "original_query": "list projects",
          "query": "list my projects"
        },
        "text": "list projects",
        "timestamp": "2025-06-14T20:38:20.587754",
        "type": "provide_information"
      },
      {
        "parameters": {
          "_prevent_speech": true,
          "original_query": "open curs"
        },
        "text": "open curs",
        "timestamp": "2025-06-14T20:39:47.701909",
        "type": "provide_information"
      },
      {
        "parameters": {
          "_prevent_speech": true,
          "original_query": "open cursor"
        },
        "text": "open cursor",
        "timestamp": "2025-06-14T20:40:00.789520",
        "type": "provide_information"
      },
      {
        "parameters": {
          "_prevent_speech": true,
          "original_query": "open curs"
        },
        "text": "open curs",
        "timestamp": "2025-06-14T20:40:13.057505",
        "type": "provide_information"
      },
      {
        "parameters": {
          "original_query": "open curs"
        },
        "text": "open curs",
        "timestamp": "2025-06-14T20:40:25.356494",
        "type": "provide_information"
      },
      {
        "parameters": {
          "app_name": "vscode",
          "operation": "launch",
          "original_query": "open vs"
        },
        "text": "open vs",
        "timestamp": "2025-06-14T20:41:10.080923",
        "type": "app_control"
      },
      {
        "parameters": {
          "app_name": "curs",
          "operation": "launch",
          "original_query": "open curs"
        },
        "text": "open curs",
        "timestamp": "2025-06-14T20:41:23.845449",
        "type": "app_control"
      },
      {
        "parameters": {
          "app_name": "discord",
          "operation": "launch",
          "original_query": "open discord"
        },
        "text": "open discord",
        "timestamp": "2025-06-14T20:41:52.991113",
        "type": "app_control"
      },
      {
        "parameters": {
          "app_name": "discord",
          "operation": "launch",
          "original_query": "open discord"
        },
        "text": "open discord",
        "timestamp": "2025-06-14T20:42:56.024810",
        "type": "app_control"
      },
      {
        "parameters": {
          "_prevent_speech": true,
          "original_query": "list applications"
        },
        "text": "list applications",
        "timestamp": "2025-06-14T20:44:34.017289",
        "type": "provide_information"
      },
      {
        "parameters": {
          "_prevent_speech": true,
          "original_query": "show installed application",
          "query": "show installed application"
        },
        "text": "show installed application",
        "timestamp": "2025-06-14T20:46:34.071466",
        "type": "provide_information"
      },
      {
        "parameters": {
          "_prevent_speech": true,
          "original_query": "installed applications"
        },
        "text": "installed applications",
        "timestamp": "2025-06-14T20:48:28.060183",
        "type": "provide_information"
      },
      {
        "parameters": {
          "_prevent_speech": true,
          "original_query": "list applications"
        },
        "text": "list applications",
        "timestamp": "2025-06-14T20:50:10.209669",
        "type": "provide_information"
      },
      {
        "parameters": {
          "operation": "off",
          "original_query": "turn off the fan"
        },
        "text": "turn off the fan",
        "timestamp": "2025-06-14T20:55:43.135991",
        "type": "fan_control"
      },
      {
        "parameters": {
          "operation": "off",
          "original_query": "turn off the fan"
        },
        "text": "turn off the fan",
        "timestamp": "2025-06-15T12:45:24.958620",
        "type": "fan_control"
      },
      {
        "parameters": {
          "operation": "on",
          "original_query": "turn on the fan"
        },
        "text": "turn on the fan",
        "timestamp": "2025-06-15T12:52:32.119988",
        "type": "fan_control"
      },
      {
        "parameters": {
          "_prevent_speech": true,
          "original_query": "what's the fan",
          "query": "what's the fan"
        },
        "text": "what's the fan",
        "timestamp": "2025-06-15T12:53:21.884312",
        "type": "provide_information"
      },
      {
        "parameters": {
          "operation": "status",
          "original_query": "what's the fan status"
        },
        "text": "what's the fan status",
        "timestamp": "2025-06-15T12:53:41.530414",
        "type": "fan_control"
      },
      {
        "parameters": {
          "operation": "off",
          "original_query": "turn off the fan"
        },
        "text": "turn off the fan",
        "timestamp": "2025-06-15T14:42:21.667333",
        "type": "fan_control"
      },
      {
        "parameters": {
          "operation": "on",
          "original_query": "turn on the fan"
        },
        "text": "turn on the fan",
        "timestamp": "2025-06-15T15:17:42.474305",
        "type": "fan_control"
      },
      {
        "parameters": {
          "operation": "status",
          "original_query": "what's the fan status"
        },
        "text": "what's the fan status",
        "timestamp": "2025-06-15T15:17:56.775768",
        "type": "fan_control"
      },
      {
        "parameters": {
          "operation": "status",
          "original_query": "what's the fan status"
        },
        "text": "what's the fan status",
        "timestamp": "2025-06-15T15:18:15.448223",
        "type": "fan_control"
      },
      {
        "parameters": {
          "_prevent_speech": true,
          "original_query": "what's the fan status"
        },
        "text": "what's the fan status",
        "timestamp": "2025-06-15T15:19:31.704701",
        "type": "provide_information"
      },
      {
        "parameters": {
          "_prevent_speech": true,
          "original_query": "what's the fan"
        },
        "text": "what's the fan",
        "timestamp": "2025-06-15T15:19:44.547072",
        "type": "provide_information"
      },
      {
        "parameters": {
          "app_name": "VSCode",
          "operation": "launch",
          "original_query": "open cursor"
        },
        "text": "open cursor",
        "timestamp": "2025-06-15T15:19:57.098856",
        "type": "app_control"
      },
      {
        "parameters": {
          "app_name": "curse",
          "operation": "launch",
          "original_query": "open curse application"
        },
        "text": "open curse application",
        "timestamp": "2025-06-15T15:20:13.410605",
        "type": "app_control"
      },
      {
        "parameters": {
          "app_name": "cursor",
          "operation": "launch",
          "original_query": "open cursor application"
        },
        "text": "open cursor application",
        "timestamp": "2025-06-15T15:20:41.687259",
        "type": "app_control"
      },
      {
        "parameters": {
          "_prevent_speech": true,
          "original_query": "what's the famous status"
        },
        "text": "what's the famous status",
        "timestamp": "2025-06-15T15:21:27.155168",
        "type": "provide_information"
      },
      {
        "parameters": {
          "operation": "status",
          "original_query": "what's the fan status"
        },
        "text": "what's the fan status",
        "timestamp": "2025-06-15T15:21:41.625847",
        "type": "fan_control"
      },
      {
        "parameters": {
          "operation": "status",
          "original_query": "what's the fan status"
        },
        "text": "what's the fan status",
        "timestamp": "2025-06-15T15:23:48.618349",
        "type": "fan_control"
      },
      {
        "parameters": {
          "operation": "status",
          "original_query": "what's the fan status"
        },
        "text": "what's the fan status",
        "timestamp": "2025-06-15T15:24:52.051545",
        "type": "fan_control"
      },
      {
        "parameters": {
          "operation": "status",
          "original_query": "what's the fan status"
        },
        "text": "what's the fan status",
        "timestamp": "2025-06-15T15:29:26.165521",
        "type": "fan_control"
      },
      {
        "parameters": {
          "operation": "status",
          "original_query": "what's the fan status"
        },
        "text": "what's the fan status",
        "timestamp": "2025-06-15T15:35:00.203930",
        "type": "fan_control"
      },
      {
        "parameters": {
          "original_query": "how are you"
        },
        "text": "how are you",
        "timestamp": "2025-06-15T15:38:29.805164",
        "type": "provide_information"
      },
      {
        "parameters": {
          "_prevent_speech": true,
          "original_query": "hey how are you"
        },
        "text": "hey how are you",
        "timestamp": "2025-06-15T15:39:12.592936",
        "type": "provide_information"
      },
      {
        "parameters": {
          "operation": "status",
          "original_query": "what's the fan status"
        },
        "text": "what's the fan status",
        "timestamp": "2025-06-15T15:39:32.501618",
        "type": "fan_control"
      },
      {
        "parameters": {
          "operation": "status",
          "original_query": "what's the fan status"
        },
        "text": "what's the fan status",
        "timestamp": "2025-06-15T15:41:26.411474",
        "type": "fan_control"
      },
      {
        "parameters": {
          "_prevent_speech": true,
          "original_query": "hi how are you",
          "query": "conversation"
        },
        "text": "hi how are you",
        "timestamp": "2025-06-15T15:46:31.105742",
        "type": "provide_information"
      },
      {
        "parameters": {
          "operation": "status",
          "original_query": "what is the fan status"
        },
        "text": "what is the fan status",
        "timestamp": "2025-06-15T15:47:11.193086",
        "type": "fan_control"
      },
      {
        "timestamp": "2025-06-15T15:47:33.910998",
        "type": "fan_control",
        "text": "what is the fan status",
        "parameters": {
          "operation": "status",
          "original_query": "what is the fan status"
        }
      },
      {
        "timestamp": "2025-06-15T15:53:42.378904",
        "type": "fan_control",
        "text": "what is the fan status",
        "parameters": {
          "operation": "status",
          "original_query": "what is the fan status"
        }
      },
      {
        "timestamp": "2025-06-15T15:53:52.847609",
        "type": "fan_control",
        "text": "what is the fan status",
        "parameters": {
          "operation": "status",
          "original_query": "what is the fan status"
        }
      },
      {
        "timestamp": "2025-06-15T15:54:04.519182",
        "type": "fan_control",
        "text": "what is the fan status",
        "parameters": {
          "operation": "status",
          "original_query": "what is the fan status"
        }
      },
      {
        "timestamp": "2025-06-15T16:11:58.692046",
        "type": "fan_control",
        "text": "increase the fan speed",
        "parameters": {
          "operation": "speed_up",
          "original_query": "increase the fan speed"
        }
      },
      {
        "timestamp": "2025-06-15T16:12:55.411086",
        "type": "fan_control",
        "text": "change the fan",
        "parameters": {
          "operation": "change",
          "original_query": "change the fan",
          "_prevent_speech": true
        }
      },
      {
        "timestamp": "2025-06-15T16:13:11.190160",
        "type": "fan_control",
        "text": "change the fan speed",
        "parameters": {
          "operation": "speed",
          "original_query": "change the fan speed",
          "_prevent_speech": true
        }
      },
      {
        "timestamp": "2025-06-15T16:13:59.246480",
        "type": "fan_control",
        "text": "what the fan status",
        "parameters": {
          "operation": "status",
          "original_query": "what the fan status"
        }
      },
      {
        "timestamp": "2025-06-15T16:14:12.919972",
        "type": "provide_information",
        "text": "what's the famous status",
        "parameters": {
          "original_query": "what's the famous status",
          "_prevent_speech": true
        }
      },
      {
        "timestamp": "2025-06-15T16:14:25.853139",
        "type": "fan_control",
        "text": "what the fan status",
        "parameters": {
          "operation": "status",
          "original_query": "what the fan status"
        }
      },
      {
        "timestamp": "2025-06-15T16:25:13.128567",
        "type": "fan_control",
        "text": "what's the fan status",
        "parameters": {
          "operation": "status",
          "original_query": "what's the fan status"
        }
      },
      {
        "timestamp": "2025-06-15T16:25:26.376258",
        "type": "fan_control",
        "text": "what's the fan status",
        "parameters": {
          "operation": "status",
          "original_query": "what's the fan status"
        }
      },
      {
        "timestamp": "2025-06-15T16:25:37.781291",
        "type": "fan_control",
        "text": "what's the fan status",
        "parameters": {
          "operation": "status",
          "original_query": "what's the fan status"
        }
      },
      {
        "timestamp": "2025-06-15T16:25:50.113240",
        "type": "fan_control",
        "text": "what's the fan status",
        "parameters": {
          "operation": "status",
          "original_query": "what's the fan status"
        }
      },
      {
        "timestamp": "2025-06-15T16:26:02.415147",
        "type": "fan_control",
        "text": "stop",
        "parameters": {
          "operation": "off",
          "original_query": "stop"
        }
      }
    ],
    "last_commands": [
      "change the fan",
      "change the fan speed",
      "what the fan status",
      "what's the famous status",
      "what the fan status",
      "what's the fan status",
      "what's the fan status",
      "what's the fan status",
      "what's the fan status",
      "stop"
    ],
    "total_commands": 349,
    "total_sessions": 69
  },
  "patterns": {
    "frequent_apps": {},
    "frequent_searches": {},
    "time_patterns": {
      "afternoon": [],
      "evening": [],
      "morning": [],
      "night": []
    }
  },
  "favorites": {
    "applications": [],
    "directories": [],
    "files": [],
    "websites": []
  }
}